Metadata-Version: 2.1
Name: opydoviz-kurlari
Version: 1.2
Summary: Python ile guncel doviz kurlarini goruntuleyin.
Home-page: https://github.com/muhammedcamsari/opydoviz-kurlari
Author: Muhammed Çamsarı
Author-email: Muhammedcamsari@icloud.com
License: MIT
Platform: UNKNOWN
Classifier: Programming Language :: Python :: 3
Classifier: License :: OSI Approved :: MIT License
Classifier: Natural Language :: Turkish
Classifier: Operating System :: OS Independent
